{
  "className": "Dz3DViewport",
  "members": [
    {
      "name": "modal",
      "signature": "modal: boolean;",
      "kind": "property",
      "paramCount": 0
    },
    {
      "name": "windowModality",
      "signature": "windowModality: number;",
      "kind": "property",
      "paramCount": 0
    },
    {
      "name": "geometry",
      "signature": "geometry: QObject;",
      "kind": "property",
      "paramCount": 0
    },
    {
      "name": "frameGeometry",
      "signature": "frameGeometry: QObject;",
      "kind": "property",
      "paramCount": 0
    },
    {
      "name": "normalGeometry",
      "signature": "normalGeometry: QObject;",
      "kind": "property",
      "paramCount": 0
    },
    {
      "name": "pos",
      "signature": "pos: QObject;",
      "kind": "property",
      "paramCount": 0
    },
    {
      "name": "frameSize",
      "signature": "frameSize: QObject;",
      "kind": "property",
      "paramCount": 0
    },
    {
      "name": "size",
      "signature": "size: QObject;",
      "kind": "property",
      "paramCount": 0
    },
    {
      "name": "rect",
      "signature": "rect: QObject;",
      "kind": "property",
      "paramCount": 0
    },
    {
      "name": "childrenRect",
      "signature": "childrenRect: QObject;",
      "kind": "property",
      "paramCount": 0
    },
    {
      "name": "childrenRegion",
      "signature": "childrenRegion: QObject;",
      "kind": "property",
      "paramCount": 0
    },
    {
      "name": "minimumSize",
      "signature": "minimumSize: QObject;",
      "kind": "property",
      "paramCount": 0
    },
    {
      "name": "maximumSize",
      "signature": "maximumSize: QObject;",
      "kind": "property",
      "paramCount": 0
    },
    {
      "name": "minimumWidth",
      "signature": "minimumWidth: number;",
      "kind": "property",
      "paramCount": 0
    },
    {
      "name": "minimumHeight",
      "signature": "minimumHeight: number;",
      "kind": "property",
      "paramCount": 0
    },
    {
      "name": "maximumWidth",
      "signature": "maximumWidth: number;",
      "kind": "property",
      "paramCount": 0
    },
    {
      "name": "maximumHeight",
      "signature": "maximumHeight: number;",
      "kind": "property",
      "paramCount": 0
    },
    {
      "name": "sizeIncrement",
      "signature": "sizeIncrement: QObject;",
      "kind": "property",
      "paramCount": 0
    },
    {
      "name": "baseSize",
      "signature": "baseSize: QObject;",
      "kind": "property",
      "paramCount": 0
    },
    {
      "name": "cursor",
      "signature": "cursor: QObject;",
      "kind": "property",
      "paramCount": 0
    },
    {
      "name": "mouseTracking",
      "signature": "mouseTracking: boolean;",
      "kind": "property",
      "paramCount": 0
    },
    {
      "name": "isActiveWindow",
      "signature": "isActiveWindow: boolean;",
      "kind": "property",
      "paramCount": 0
    },
    {
      "name": "focus",
      "signature": "focus: boolean;",
      "kind": "property",
      "paramCount": 0
    },
    {
      "name": "contextMenuPolicy",
      "signature": "contextMenuPolicy: number;",
      "kind": "property",
      "paramCount": 0
    },
    {
      "name": "updatesEnabled",
      "signature": "updatesEnabled: boolean;",
      "kind": "property",
      "paramCount": 0
    },
    {
      "name": "minimized",
      "signature": "minimized: boolean;",
      "kind": "property",
      "paramCount": 0
    },
    {
      "name": "maximized",
      "signature": "maximized: boolean;",
      "kind": "property",
      "paramCount": 0
    },
    {
      "name": "fullScreen",
      "signature": "fullScreen: boolean;",
      "kind": "property",
      "paramCount": 0
    },
    {
      "name": "sizeHint",
      "signature": "sizeHint: QObject;",
      "kind": "property",
      "paramCount": 0
    },
    {
      "name": "acceptDrops",
      "signature": "acceptDrops: boolean;",
      "kind": "property",
      "paramCount": 0
    },
    {
      "name": "windowTitle",
      "signature": "windowTitle: string;",
      "kind": "property",
      "paramCount": 0
    },
    {
      "name": "windowIcon",
      "signature": "windowIcon: QObject;",
      "kind": "property",
      "paramCount": 0
    },
    {
      "name": "windowIconText",
      "signature": "windowIconText: string;",
      "kind": "property",
      "paramCount": 0
    },
    {
      "name": "windowOpacity",
      "signature": "windowOpacity: number;",
      "kind": "property",
      "paramCount": 0
    },
    {
      "name": "windowModified",
      "signature": "windowModified: boolean;",
      "kind": "property",
      "paramCount": 0
    },
    {
      "name": "accessibleName",
      "signature": "accessibleName: string;",
      "kind": "property",
      "paramCount": 0
    },
    {
      "name": "accessibleDescription",
      "signature": "accessibleDescription: string;",
      "kind": "property",
      "paramCount": 0
    },
    {
      "name": "layoutDirection",
      "signature": "layoutDirection: number;",
      "kind": "property",
      "paramCount": 0
    },
    {
      "name": "autoFillBackground",
      "signature": "autoFillBackground: boolean;",
      "kind": "property",
      "paramCount": 0
    },
    {
      "name": "styleSheet",
      "signature": "styleSheet: string;",
      "kind": "property",
      "paramCount": 0
    },
    {
      "name": "locale",
      "signature": "locale: QObject;",
      "kind": "property",
      "paramCount": 0
    },
    {
      "name": "windowFilePath",
      "signature": "windowFilePath: string;",
      "kind": "property",
      "paramCount": 0
    },
    {
      "name": "inputMethodHints",
      "signature": "inputMethodHints: number;",
      "kind": "property",
      "paramCount": 0
    },
    {
      "name": "NO_FLOOR",
      "signature": "NO_FLOOR: number;",
      "kind": "property",
      "paramCount": 0
    },
    {
      "name": "WIRE_FLOOR",
      "signature": "WIRE_FLOOR: number;",
      "kind": "property",
      "paramCount": 0
    },
    {
      "name": "SOLID_FLOOR",
      "signature": "SOLID_FLOOR: number;",
      "kind": "property",
      "paramCount": 0
    },
    {
      "name": "WIRE_BOX",
      "signature": "WIRE_BOX: number;",
      "kind": "property",
      "paramCount": 0
    },
    {
      "name": "SOLID_BOX",
      "signature": "SOLID_BOX: number;",
      "kind": "property",
      "paramCount": 0
    },
    {
      "name": "WIREFRAME",
      "signature": "WIREFRAME: number;",
      "kind": "property",
      "paramCount": 0
    },
    {
      "name": "LIT_WIREFRAME",
      "signature": "LIT_WIREFRAME: number;",
      "kind": "property",
      "paramCount": 0
    },
    {
      "name": "HIDDEN_LINE",
      "signature": "HIDDEN_LINE: number;",
      "kind": "property",
      "paramCount": 0
    },
    {
      "name": "WIRE_SHADED",
      "signature": "WIRE_SHADED: number;",
      "kind": "property",
      "paramCount": 0
    },
    {
      "name": "SMOOTH_SHADED",
      "signature": "SMOOTH_SHADED: number;",
      "kind": "property",
      "paramCount": 0
    },
    {
      "name": "WIRE_TEXTURED",
      "signature": "WIRE_TEXTURED: number;",
      "kind": "property",
      "paramCount": 0
    },
    {
      "name": "TEXTURED",
      "signature": "TEXTURED: number;",
      "kind": "property",
      "paramCount": 0
    },
    {
      "name": "AnchorTopLeft",
      "signature": "AnchorTopLeft: number;",
      "kind": "property",
      "paramCount": 0
    },
    {
      "name": "AnchorTopRight",
      "signature": "AnchorTopRight: number;",
      "kind": "property",
      "paramCount": 0
    },
    {
      "name": "AnchorBottomLeft",
      "signature": "AnchorBottomLeft: number;",
      "kind": "property",
      "paramCount": 0
    },
    {
      "name": "AnchorBottomRight",
      "signature": "AnchorBottomRight: number;",
      "kind": "property",
      "paramCount": 0
    },
    {
      "name": "customContextMenuRequested",
      "signature": "customContextMenuRequested(): any; // TODO ;",
      "kind": "method",
      "paramCount": 0
    },
    {
      "name": "setEnabled",
      "signature": "setEnabled(): any; // TODO ;",
      "kind": "method",
      "paramCount": 0
    },
    {
      "name": "setDisabled",
      "signature": "setDisabled(): any; // TODO ;",
      "kind": "method",
      "paramCount": 0
    },
    {
      "name": "setWindowModified",
      "signature": "setWindowModified(): any; // TODO ;",
      "kind": "method",
      "paramCount": 0
    },
    {
      "name": "setWindowTitle",
      "signature": "setWindowTitle(): any; // TODO ;",
      "kind": "method",
      "paramCount": 0
    },
    {
      "name": "setStyleSheet",
      "signature": "setStyleSheet(): any; // TODO ;",
      "kind": "method",
      "paramCount": 0
    },
    {
      "name": "repaint",
      "signature": "repaint(): any; // TODO ;",
      "kind": "method",
      "paramCount": 0
    },
    {
      "name": "setVisible",
      "signature": "setVisible(): any; // TODO ;",
      "kind": "method",
      "paramCount": 0
    },
    {
      "name": "setHidden",
      "signature": "setHidden(): any; // TODO ;",
      "kind": "method",
      "paramCount": 0
    },
    {
      "name": "show",
      "signature": "show(): any; // TODO ;",
      "kind": "method",
      "paramCount": 0
    },
    {
      "name": "hide",
      "signature": "hide(): any; // TODO ;",
      "kind": "method",
      "paramCount": 0
    },
    {
      "name": "setShown",
      "signature": "setShown(): any; // TODO ;",
      "kind": "method",
      "paramCount": 0
    },
    {
      "name": "showMinimized",
      "signature": "showMinimized(): any; // TODO ;",
      "kind": "method",
      "paramCount": 0
    },
    {
      "name": "showMaximized",
      "signature": "showMaximized(): any; // TODO ;",
      "kind": "method",
      "paramCount": 0
    },
    {
      "name": "showFullScreen",
      "signature": "showFullScreen(): any; // TODO ;",
      "kind": "method",
      "paramCount": 0
    },
    {
      "name": "showNormal",
      "signature": "showNormal(): any; // TODO ;",
      "kind": "method",
      "paramCount": 0
    },
    {
      "name": "close",
      "signature": "close(): any; // TODO ;",
      "kind": "method",
      "paramCount": 0
    },
    {
      "name": "raise",
      "signature": "raise(): any; // TODO ;",
      "kind": "method",
      "paramCount": 0
    },
    {
      "name": "lower",
      "signature": "lower(): any; // TODO ;",
      "kind": "method",
      "paramCount": 0
    },
    {
      "name": "updateMicroFocus",
      "signature": "updateMicroFocus(): any; // TODO ;",
      "kind": "method",
      "paramCount": 0
    },
    {
      "name": "pickNodes",
      "signature": "pickNodes(area: QPolygonF, nodes: DzNode[], useSelectionMaps: boolean): void;",
      "kind": "method",
      "paramCount": 3
    },
    {
      "name": "pickNodes",
      "signature": "pickNodes(area: QPolygonF, nodes: DzNode[], useSelectionMaps: boolean): void;",
      "kind": "method",
      "paramCount": 3
    },
    {
      "name": "pickMaterials",
      "signature": "pickMaterials(area: QPolygonF, mats: DzMaterial[]): void;",
      "kind": "method",
      "paramCount": 2
    },
    {
      "name": "pickFacets",
      "signature": "pickFacets(area: QPolygonF, facets: number[], facetNode: DzNode): void;",
      "kind": "method",
      "paramCount": 3
    },
    {
      "name": "pickGizmos",
      "signature": "pickGizmos(area: QPolygonF, gizmos: number[]): void;",
      "kind": "method",
      "paramCount": 2
    },
    {
      "name": "appendHoverCursor",
      "signature": "appendHoverCursor(cursor: QCursor): void;",
      "kind": "method",
      "paramCount": 1
    },
    {
      "name": "updateGLOptions",
      "signature": "updateGLOptions(): void;",
      "kind": "method",
      "paramCount": 0
    },
    {
      "name": "updateView",
      "signature": "updateView(): void;",
      "kind": "method",
      "paramCount": 0
    },
    {
      "name": "removeCamera",
      "signature": "removeCamera(cam: DzNode): void;",
      "kind": "method",
      "paramCount": 1
    }
  ]
}